.hgignore
.hgtags
CHANGES.rst
MANIFEST.in
README.rst
setup.py
ircnotifier/__init__.py
ircnotifier/main.py
ircnotifier/webapi.py
ircnotifier.egg-info/PKG-INFO
ircnotifier.egg-info/SOURCES.txt
ircnotifier.egg-info/dependency_links.txt
ircnotifier.egg-info/entry_points.txt
ircnotifier.egg-info/not-zip-safe
ircnotifier.egg-info/requires.txt
ircnotifier.egg-info/top_level.txt
ircnotifier/htdocs/index.html
scripts/ircnotifier
scripts/message