Metadata-Version: 1.0
Name: ircnotifier
Version: 0.0.2
Summary: Python IRC Notifier Daemon with RESTful API using circuits
Home-page: TBA
Author: James Mills
Author-email: James Mills, prologic at shortcircuit dot net dot au
License: MIT
Download-URL: TBA
Keywords: Python IRC Notifier Daemon
Platform: POSIX
